awsclimfa/__init__.py
awsclimfa/main.py
awsclimfa/log/__init__.py
awsclimfa/log/config.yaml
awsclimfa/log/logger.py
aws_cli_mfa-0.1.1b0.dist-info/LICENSE
aws_cli_mfa-0.1.1b0.dist-info/METADATA
aws_cli_mfa-0.1.1b0.dist-info/WHEEL
aws_cli_mfa-0.1.1b0.dist-info/entry_points.txt
aws_cli_mfa-0.1.1b0.dist-info/top_level.txt
aws_cli_mfa-0.1.1b0.dist-info/RECORD
