Metadata-Version: 2.1
Name: aws-cli-mfa
Version: 0.1.1b0
Summary: It can help you to access AWS resources through AWS CLI with MFA token
Home-page: https://github.com/no-brand/aws-cli-mfa
Author: no-brand
Author-email: do.dream.david@gmail.com
License: MIT
Platform: UNKNOWN
Requires-Dist: boto3
